aws/osml/models/__init__.py
aws/osml/models/server_utils.py
aws/osml/models/aircraft/__init__.py
aws/osml/models/aircraft/app.py
aws/osml/models/centerpoint/__init__.py
aws/osml/models/centerpoint/app.py
aws/osml/models/flood/__init__.py
aws/osml/models/flood/app.py
osml_models-1.2.0.dist-info/LICENSE
osml_models-1.2.0.dist-info/METADATA
osml_models-1.2.0.dist-info/WHEEL
osml_models-1.2.0.dist-info/top_level.txt
osml_models-1.2.0.dist-info/RECORD
