Metadata-Version: 2.1
Name: osml-models
Version: 1.2.0
Summary: A set of demonstration models to test OSML with.
Author: Amazon Web Services
Author-email: todo-public-library-poc@amazon.com
License: 
Project-URL: Source, https://github.com/aws-solutions-library-samples/osml-models
Project-URL: Tracker, https://github.com/aws-solutions-library-samples/osml-models/issues
Classifier: Programming Language :: Python :: 3
Classifier: Operating System :: OS Independent
Requires-Python: >=3.9
License-File: LICENSE
Requires-Dist: json-logging==1.3.0
Requires-Dist: boto3==1.34.104
Requires-Dist: setuptools==68.0.0
Requires-Dist: argparse==1.4.0
Requires-Dist: flask==2.3.3
Requires-Dist: waitress==2.1.2
Requires-Dist: shapely==2.0.1
Requires-Dist: matplotlib==3.7.2
Provides-Extra: gdal
Requires-Dist: gdal>=3.7.0; extra == "gdal"
Provides-Extra: test
Requires-Dist: tox; extra == "test"
